{
  "kind": "collectionType",
  "collectionName": "movies",
  "info": {
    "singularName": "movie",
    "pluralName": "movies",
    "displayName": "movie"
  },
  "options": {
    "draftAndPublish": true
  },
  "pluginOptions": {},
  "attributes": {
    "bmx_movies": {
      "type": "relation",
      "relation": "oneToMany",
      "target": "api::bmx-movie.bmx-movie"
    },
    "dirt_bike_movies": {
      "type": "relation",
      "relation": "oneToMany",
      "target": "api::dirt-bike-movie.dirt-bike-movie"
    },
    "skate_movies": {
      "type": "relation",
      "relation": "oneToMany",
      "target": "api::skate-movie.skate-movie"
    },
    "snowboard_movies": {
      "type": "relation",
      "relation": "oneToMany",
      "target": "api::snowboard-movie.snowboard-movie"
    },
    "surf_movies": {
      "type": "relation",
      "relation": "oneToMany",
      "target": "api::surf-movie.surf-movie"
    }
  }
}
